MANIFEST.in
board_hr_evaluation_view.xml
hr_evaluation_data.xml
hr_evaluation_demo.xml
hr_evaluation_installer.xml
hr_evaluation_view.xml
setup.py
./__init__.py
./__openerp__.py
./hr_evaluation.py
./report/__init__.py
./report/hr_evaluation_report.py
i18n/ar.po
i18n/bg.po
i18n/ca.po
i18n/cs.po
i18n/da.po
i18n/de.po
i18n/es.po
i18n/es_CR.po
i18n/es_EC.po
i18n/es_MX.po
i18n/es_VE.po
i18n/et.po
i18n/fi.po
i18n/fr.po
i18n/gl.po
i18n/hr.po
i18n/hr_evaluation.pot
i18n/hu.po
i18n/id.po
i18n/it.po
i18n/ja.po
i18n/mk.po
i18n/mn.po
i18n/nl.po
i18n/pl.po
i18n/pt.po
i18n/pt_BR.po
i18n/ro.po
i18n/ru.po
i18n/sl.po
i18n/sr.po
i18n/sr@latin.po
i18n/sv.po
i18n/tr.po
i18n/zh_CN.po
i18n/zh_TW.po
images/hr_evaluation.jpeg
images/hr_evaluation_analysis.jpeg
images/hr_interview_requests.jpeg
openerp_hr_evaluation.egg-info/PKG-INFO
openerp_hr_evaluation.egg-info/SOURCES.txt
openerp_hr_evaluation.egg-info/dependency_links.txt
openerp_hr_evaluation.egg-info/requires.txt
openerp_hr_evaluation.egg-info/top_level.txt
report/hr_evaluation_report_view.xml
security/hr_evaluation_security.xml
security/ir.model.access.csv
specifications/evaluation_plan.png
static/src/img/icon.png
test/hr_evalution_demo.yml
test/test_hr_evaluation.yml